{
  "id": 7484527,
  "name": "2025 WINTER SCARF (FREE)",
  "permalink": "2025-winter-scarf-free",
  "url": "https://www.ravelry.com/patterns/library/2025-winter-scarf-free",
  "external_url": "https://the-longweekend.com/products/2025-winter-scarf-knitting-pattern-free",
  "designer_name": "Weekend Knits",
  "project_type": "Scarf",
  "fiber_art": "Knitting",
  "yarn_weight": "Worsted",
  "materials": [
    {
      "fiber": "Heavy Merino",
      "pct": null
    }
  ],
  "stitches_used": [
    "Single crochet (sc)",
    "Stockinette stitch",
    "Treble crochet (tr)"
  ],
  "techniques_used": [
    "Bottom-up",
    "In the round"
  ],
  "hook_sizes_mm": [],
  "needle_sizes_mm": [
    5.0
  ],
  "published": "2025/12/01",
  "sizes_available": "One size",
  "rating_average": 4.5,
  "rating_count": 4,
  "difficulty_average": 2.0,
  "favorites_count": 309,
  "projects_count": 25,
  "free_ravelry_download": false,
  "download_url": "https://the-longweekend.com/products/2025-winter-scarf-knitting-pattern-free"
}