{
  "id": 7392113,
  "name": "253-57  Festive Nordic Mittens",
  "permalink": "253-57-festive-nordic-mittens",
  "url": "https://www.ravelry.com/patterns/library/253-57-festive-nordic-mittens",
  "external_url": "https://www.garnstudio.com/pattern.php?id=12051&cid=19",
  "designer_name": "DROPS design",
  "project_type": "Mittens/Gloves",
  "fiber_art": "Knitting",
  "yarn_weight": "DK",
  "materials": [
    {
      "fiber": "DROPS Lima",
      "pct": null
    }
  ],
  "stitches_used": [
    "Stockinette stitch",
    "Treble crochet (tr)"
  ],
  "techniques_used": [
    "Bottom-up",
    "Charted",
    "In the round",
    "Seamless",
    "Stranded colorwork",
    "Written"
  ],
  "hook_sizes_mm": [],
  "needle_sizes_mm": [
    3.0
  ],
  "published": "2024/12/01",
  "sizes_available": "S/M – M/L",
  "rating_average": 4.583333333333333,
  "rating_count": 12,
  "difficulty_average": 3.0,
  "favorites_count": 1856,
  "projects_count": 60,
  "free_ravelry_download": false,
  "download_url": "https://www.garnstudio.com/pattern.php?id=12051&cid=19"
}