{
  "id": 7374419,
  "name": "48-20  Lily Leaper Socks",
  "permalink": "48-20-lily-leaper-socks",
  "url": "https://www.ravelry.com/patterns/library/48-20-lily-leaper-socks",
  "external_url": "https://www.garnstudio.com/pattern.php?id=11970&cid=19",
  "designer_name": "DROPS design",
  "project_type": "Socks",
  "fiber_art": "Knitting",
  "yarn_weight": "DK",
  "materials": [
    {
      "fiber": "DROPS Fiesta",
      "pct": null
    }
  ],
  "stitches_used": [
    "Stockinette stitch",
    "Treble crochet (tr)"
  ],
  "techniques_used": [
    "In the round",
    "Seamless",
    "Written"
  ],
  "hook_sizes_mm": [],
  "needle_sizes_mm": [
    3.5
  ],
  "published": "2024/10/01",
  "sizes_available": " 24/25-26/28-29/31-32/34-35/37-38/40-41/43",
  "rating_average": 4.666666666666667,
  "rating_count": 3,
  "difficulty_average": 2.0,
  "favorites_count": 77,
  "projects_count": 34,
  "free_ravelry_download": false,
  "download_url": "https://www.garnstudio.com/pattern.php?id=11970&cid=19"
}