{
  "id": 7458556,
  "name": "Boo-tiful Ghost Mosaic Motif",
  "permalink": "boo-tiful-ghost-mosaic-motif",
  "url": "https://www.ravelry.com/patterns/library/boo-tiful-ghost-mosaic-motif",
  "external_url": "https://www.elimeedesigns.co.uk/blog/boo-tiful-ghost-mosaic-motif-crochet-pattern",
  "designer_name": "Elimee Designs",
  "project_type": "Blanket",
  "fiber_art": "Crochet",
  "yarn_weight": "DK",
  "materials": [
    {
      "fiber": "Baby Twinkle DK",
      "pct": null
    },
    {
      "fiber": "Special Double Knit",
      "pct": null
    }
  ],
  "stitches_used": [
    "Single crochet (sc)",
    "Treble crochet (tr)"
  ],
  "techniques_used": [
    "Bottom-up",
    "Mosaic",
    "Written"
  ],
  "hook_sizes_mm": [
    4.0
  ],
  "needle_sizes_mm": [],
  "published": "2025/09/01",
  "sizes_available": "Can be adjusted to make any size.",
  "rating_average": 0,
  "rating_count": null,
  "difficulty_average": 0,
  "favorites_count": 110,
  "projects_count": 10,
  "free_ravelry_download": false,
  "download_url": "http://www.ravelry.com/purchase/elimee-designs-designs/1021897"
}