{
  "id": 7322848,
  "name": "bunny puff",
  "permalink": "bunny-puff",
  "url": "https://www.ravelry.com/patterns/library/bunny-puff",
  "external_url": "https://www.sweetsofties.com/2024/03/bunny-puff.html",
  "designer_name": "sweet softies",
  "project_type": "toys",
  "fiber_art": "crochet",
  "yarn_weight": "bulky",
  "materials": [
    {
      "fiber": "Polyester (Polyester)",
      "pct": 100.0
    }
  ],
  "stitches_used": [
    "double crochet (dc)",
    "half double crochet (hdc)",
    "puff stitch",
    "single crochet (sc)",
    "treble crochet (tr)"
  ],
  "techniques_used": [
    "in the round",
    "seamless",
    "top-down",
    "written"
  ],
  "hook_sizes_mm": [
    5.0
  ],
  "needle_sizes_mm": [],
  "published": "2024/03/01",
  "sizes_available": "",
  "rating_average": 4.428571428571429,
  "rating_count": 7,
  "difficulty_average": 1.6,
  "favorites_count": 1115,
  "projects_count": 34,
  "free_ravelry_download": false,
  "download_url": "http://www.ravelry.com/purchase/sweet-softies/915666",
  "notes": "free pattern page and video tutorial: https://www.sweetsofties.com/2024/03/bunny-puff.html\r\n\r\nget the yarn kit here: https://yarnsea.com/en/project/2127/bunny-puff\r\n\r\nthe bunny puff amigurumi pattern is no-sew, beginner friendly, and quick to work up. it’s similar to the squishy marshmallow easter peeps candy, but cuter and more 3d! this design can be crocheted with different yarn weights and fibers to create varying results, such as super bulky blanket or chenille yarn for a plush velvet look, and a medium weight yarn in acrylic or cotton for an even smaller keychain version. \r\n     it’s the perfect last-minute present to whip up for class valentine’s day gifts, non-candy easter egg treats, holiday gifts, or christmas stocking stuffers. it’s also great as a market prep product for craft fairs since it’s fast and easy to make.\r\n     a perfect “claw machine” amigurumi! the pdf pattern includes written pattern instructions along with a detailed photo tutorial to guide you through the doll-making process.\r\n\r\n**size**\r\nheight: 3.5” (9 cm)\r\n \r\n**materials**\r\nsuper bulky (weight 6) chenille yarn in desired colors (i used hobbii honey bunny) \r\n8mm plastic safety eyes (x2)\r\n5mm crochet hook\r\nstuffing\r\nscissors\r\n\r\n**level**\r\n★☆☆☆☆ familiar beginner. requires familiarity with stitches used (below), and attaching yarn.\r\n\r\n**stitches & techniques used (us terminology)** \r\nfo = fasten off\r\nch = chain\r\nsc = single crochet\r\ninc = increase (insert 2 sc in same st)\r\ndec = decrease (sc 2 sts together)\r\nhdc = half double crochet\r\ndc = double crochet\r\n\r\n*copyright notice · this pattern is © 2024 sweet softies, www.sweetsofties.com. for personal use only. you may not translate, distribute, copy, alter, or sell this pattern in any way. my patterns may not be used in video tutorials or for teaching classes (both online and in-person). you may link to this pattern but you may not copy any part of the pattern instructions on other websites. you may sell finished items made with this pattern if you credit sweet softies as the designer and link to my website. no wholesale.*\r\n\r\n----- social media & contact -----\r\nwebsite/blog: https://www.sweetsofties.com/\r\nyoutube channel: https://www.youtube.com/sweetsofties\r\nfacebook: https://www.facebook.com/sweetsofties\r\ninstagram: https://www.instagram.com/sweetsofties/\r\ntiktok: https://www.tiktok.com/@sweetsofties.com\r\ntwitter: http://twitter.com/sweetsofties\r\netsy: https://tidd.ly/3szw09m\r\nravelry: https://www.ravelry.com/designers/sweet-softies\r\npinterest: https://www.pinterest.com/sweetsofties"
}