{
  "id": 7491348,
  "name": "Callisto Hat",
  "permalink": "callisto-hat-2",
  "url": "https://www.ravelry.com/patterns/library/callisto-hat-2",
  "external_url": "https://kelbournewoolens.com/products/callisto-hat-pattern",
  "designer_name": "Tommy Knits",
  "project_type": "Hat",
  "fiber_art": "Knitting",
  "yarn_weight": "DK",
  "materials": [
    {
      "fiber": "Germantown DK",
      "pct": null
    }
  ],
  "stitches_used": [
    "Cable",
    "Ribbing",
    "Treble crochet (tr)"
  ],
  "techniques_used": [
    "Blocking",
    "Bottom-up",
    "Cables",
    "Charted",
    "In the round",
    "Seamless",
    "Written"
  ],
  "hook_sizes_mm": [],
  "needle_sizes_mm": [
    3.5,
    4.0
  ],
  "published": "2026/01/01",
  "sizes_available": "19\" (48 cm) brim circumference, unstretched, 12\" (30.5 cm) height, brim unfolded.",
  "rating_average": 4.666666666666667,
  "rating_count": 9,
  "difficulty_average": 4.125,
  "favorites_count": 3204,
  "projects_count": 83,
  "free_ravelry_download": true,
  "download_url": "http://www.ravelry.com/dls/13463/1047592",
  "pdf": {
    "filename": "7491348.pdf",
    "path": "C:\\Users\\PSLAVCHE\\Documents\\University\\AI\\CrochetAndKnittingSearchEngine\\pdfs\\7491348.pdf",
    "url": "https://pdf.ravelrycache.com/KelbourneWoolens/2113153/YODK_Hats_Callisto_by_Tommy_Knits.pdf?AWSAccessKeyId=AKIAJNNSUP6J3RN4WZYQ&Expires=1768479318&Signature=gcaojHfkldZ6StmoauiEoCRXLhM%3D&key_expires=1768479318&key=mB6uzb2K0tFuNyZdggUwOw",
    "size_bytes": 1939377
  }
}