{
  "id": 1364885,
  "name": "cloud cowl",
  "permalink": "cloud-cowl-9",
  "url": "https://www.ravelry.com/patterns/library/cloud-cowl-9",
  "external_url": "",
  "designer_name": "victoria magnus",
  "project_type": "shawl/wrap",
  "fiber_art": "crochet",
  "yarn_weight": "any gauge - designed for any gauge",
  "materials": [
    {
      "fiber": "Merino (Merino)",
      "pct": 61.7
    },
    {
      "fiber": "Alpaca - Suri (Alpaca)",
      "pct": 24.7
    },
    {
      "fiber": "Bombyx / Cultivated / Mulberry (Silk)",
      "pct": 8.7
    },
    {
      "fiber": "Nylon / Polyamide (Nylon)",
      "pct": 5.0
    }
  ],
  "stitches_used": [
    "cluster stitch",
    "lace",
    "single crochet (sc)",
    "treble crochet (tr)"
  ],
  "techniques_used": [
    "blocking",
    "lace",
    "written"
  ],
  "hook_sizes_mm": [
    4.0,
    5.0,
    7.0,
    8.0
  ],
  "needle_sizes_mm": [],
  "published": "2023/09/01",
  "sizes_available": "multiple sizes/variations",
  "rating_average": 0,
  "rating_count": null,
  "difficulty_average": 0,
  "favorites_count": 206,
  "projects_count": 34,
  "free_ravelry_download": true,
  "download_url": "http://www.ravelry.com/dls/2720/878625",
  "notes": "choose your cloud! \r\n\r\noriginally designed for fluffy lowther lace this pattern now comes in a variety of yarn weights. they're all free downloads so you can download the pdf that you want rather than have to scroll through the ones you don't want. \r\n\r\nwe now (oct 2024) have these versions: fluffy laceweight (in three sizes), 4ply/yarnling™️/taylor's version (in individual sizes for each), and chunky (in three sizes). \r\n\r\n**materials**\r\n\r\n*fluffy cowls*\r\n1 / 2 / 3 x 50g skeins lowther lace \r\n\r\n*yarnling cowl*\r\n24 x 5g 4ply yarnlings\r\n\r\n*4ply cowl*\r\n1 x 100g skein 4ply/fingering weight yarn \r\n\r\n*chunky cowls*\r\n1 / 2 x 100g skeins chunky weight yarn\r\n\r\n**hook size**\r\nyou will need a 4mm hook (or size required to achieve gauge)\r\nplus ideally a hook at least one or two sizes bigger for the initial chain\r\n\r\n**gauge**\r\n18sts/approx. 6 treble clusters x 13 rows/approx. 6.5 stripes to 10cm in pattern before washing and blocking.\r\n\r\nthis pattern is un-tested and hasn't been professionally tech edited by a third party - that's why it is free.\r\n\r\nalthough this is a free pattern it did require time and effort to produce and if you would like to send me a little tip for it you can do so on kofi here: https://ko-fi.com/vicecy thankyou! \r\n"
}