{
  "id": 1208175,
  "name": "Cozy Coffee Bean Socks",
  "permalink": "cozy-coffee-bean-socks",
  "url": "https://www.ravelry.com/patterns/library/cozy-coffee-bean-socks",
  "external_url": "https://kneedlesandlife.com/cozy-coffee-bean-socks-free-knitting-pattern/",
  "designer_name": "Kalley Reedy",
  "project_type": "Socks",
  "fiber_art": "Knitting",
  "yarn_weight": "Worsted",
  "materials": [
    {
      "fiber": "Classic Wool Worsted",
      "pct": null
    },
    {
      "fiber": "Wool of the Andes Worsted",
      "pct": null
    }
  ],
  "stitches_used": [
    "Cable",
    "Single crochet (sc)",
    "Treble crochet (tr)"
  ],
  "techniques_used": [
    "Cables",
    "Kitchener stitch",
    "Written"
  ],
  "hook_sizes_mm": [],
  "needle_sizes_mm": [
    3.5
  ],
  "published": "2022/01/01",
  "sizes_available": "S, M, L",
  "rating_average": 4.882352941176471,
  "rating_count": 17,
  "difficulty_average": 1.8823529411764706,
  "favorites_count": 2047,
  "projects_count": 113,
  "free_ravelry_download": false,
  "download_url": "http://www.ravelry.com/purchase/kneedles--love/750960"
}