{
  "id": 792790,
  "name": "Daisy Chain Shawl",
  "permalink": "daisy-chain-shawl-2",
  "url": "https://www.ravelry.com/patterns/library/daisy-chain-shawl-2",
  "external_url": "",
  "designer_name": "Kirsten Bishop",
  "project_type": "Shawl/Wrap",
  "fiber_art": "Crochet",
  "yarn_weight": "Fingering",
  "materials": [
    {
      "fiber": "Cotton/Acrylic 4ply",
      "pct": null
    },
    {
      "fiber": "Merino/Acrylic 4ply",
      "pct": null
    },
    {
      "fiber": "Shine Cotton/Acrylic 4ply",
      "pct": null
    },
    {
      "fiber": "Whirl",
      "pct": null
    }
  ],
  "stitches_used": [
    "Lace",
    "Treble crochet (tr)"
  ],
  "techniques_used": [
    "Lace",
    "Written"
  ],
  "hook_sizes_mm": [
    3.5
  ],
  "needle_sizes_mm": [],
  "published": "2017/11/01",
  "sizes_available": "",
  "rating_average": 4.818791946308725,
  "rating_count": 149,
  "difficulty_average": 3.572463768115942,
  "favorites_count": 11543,
  "projects_count": 473,
  "free_ravelry_download": true,
  "download_url": "http://www.ravelry.com/dls/66405/430632"
}