{
  "id": 1097773,
  "name": "Dumpster Fire amigurumi",
  "permalink": "dumpster-fire-amigurumi",
  "url": "https://www.ravelry.com/patterns/library/dumpster-fire-amigurumi",
  "external_url": "https://blog.twinkiechan.com/2020/12/21/dumpster-fire-crochet-pattern-w-100-soft/",
  "designer_name": "Twinkie Chan",
  "project_type": "Toys",
  "fiber_art": "Crochet",
  "yarn_weight": "Aran",
  "materials": [
    {
      "fiber": "Cotton Aran",
      "pct": null
    }
  ],
  "stitches_used": [
    "Single crochet (sc)",
    "Treble crochet (tr)"
  ],
  "techniques_used": [
    "Written"
  ],
  "hook_sizes_mm": [
    4.0
  ],
  "needle_sizes_mm": [],
  "published": "2020/12/01",
  "sizes_available": "",
  "rating_average": 4.769911504424779,
  "rating_count": 113,
  "difficulty_average": 4.235849056603773,
  "favorites_count": 9311,
  "projects_count": 410,
  "free_ravelry_download": false,
  "download_url": "http://www.ravelry.com/purchase/twinkie-chan-designs/663815"
}