{
  "id": 775616,
  "name": "Easy Baby Car-Seat Blanket",
  "permalink": "easy-baby-car-seat-blanket",
  "url": "https://www.ravelry.com/patterns/library/easy-baby-car-seat-blanket",
  "external_url": "https://www.woolandcompany.com/products/easy-baby-car-seat-blanket-designed-by-autumn-burns",
  "designer_name": "Autumn Burns",
  "project_type": "Blanket",
  "fiber_art": "Knitting",
  "yarn_weight": "Bulky",
  "materials": [
    {
      "fiber": "Baby Blossom Chunky",
      "pct": null
    }
  ],
  "stitches_used": [
    "Seed stitch",
    "Stockinette stitch"
  ],
  "techniques_used": [
    "Written"
  ],
  "hook_sizes_mm": [],
  "needle_sizes_mm": [
    5.5
  ],
  "published": "2017/08/01",
  "sizes_available": "One Size",
  "rating_average": 4.7265625,
  "rating_count": 128,
  "difficulty_average": 1.6507936507936507,
  "favorites_count": 2083,
  "projects_count": 489,
  "free_ravelry_download": false,
  "download_url": "https://www.woolandcompany.com/products/easy-baby-car-seat-blanket-designed-by-autumn-burns"
}