{
  "id": 643491,
  "name": "eleanor sweater scarf",
  "permalink": "eleanor-sweater-scarf",
  "url": "https://www.ravelry.com/patterns/library/eleanor-sweater-scarf",
  "external_url": "https://www.hanjancrochet.com/easy-scarf-with-sleeves-crochet-pattern/",
  "designer_name": "hannah cross",
  "project_type": "shrug",
  "fiber_art": "crochet",
  "yarn_weight": "dk",
  "materials": [
    {
      "fiber": "Acrylic (Acrylic)",
      "pct": 100.0
    }
  ],
  "stitches_used": [
    "cable",
    "double crochet (dc)",
    "half double crochet (hdc)",
    "ribbing",
    "single crochet (sc)",
    "treble crochet (tr)"
  ],
  "techniques_used": [
    "cables",
    "written"
  ],
  "hook_sizes_mm": [
    4.5
  ],
  "needle_sizes_mm": [],
  "published": "2024/09/01",
  "sizes_available": "xs/s/m, l/xl/2xl, 3xl/4xl/5xl",
  "rating_average": 4.416666666666667,
  "rating_count": 24,
  "difficulty_average": 3.347826086956522,
  "favorites_count": 6609,
  "projects_count": 141,
  "free_ravelry_download": false,
  "download_url": "http://www.ravelry.com/purchase/hanjan-crochet-designs-by-hannah-cross/689662",
  "notes": "the eleanor sweater scarf is perfect for all the seasons. the simple scarf with sleeves crochet pattern can be worn in so many ways depending on how cosy you want to feel. \r\n\r\nthis deceptively simple and versatile cover up can be a wrap cardigan, a shawl, a cowl, a regular scarf and more! made with two construction options in just one piece with simple seams for the sleeves, you’ll have it made and on in no time. \r\n\r\na great beginner crochet garment project or for anyone who wants to avoid shaping or joining. the simplicity of the construction allows the half double crochet stitch texture to shine through. crocheted using us sc and hdc stitches.\r\n\r\n*please note*-- this listing is for a pdf pattern written in english, not a finished product.\r\n\r\npattern features:\r\nsizes included: xs/s/m, l/xl/2xl, 3xl/4xl/5xl to fit chest 30” -62”\r\nskill level: easy\r\nstitch: half double crochet and single crochet\r\ninstant pdf download\r\nadjustable length and styling options \r\nfull video tutorial (to support written pattern if you are a visual learner)\r\nus crochet terms\r\nuk stitch conversion chart\r\n\r\nwhy you'll love this pattern:\r\ntwo designs in one: choose whether to work in short or long rows for your sweater scarf.\r\ngreat for weddings: the perfect shawl for a bride at a winter wedding.\r\ndetailed instructions: 12-page pdf in us crochet terms for clear, easy-to-follow guidance.\r\n\r\nmaterials needed:\r\ncategory 3 (double knit) yarn (i used amigo dk 100% acrylic,\r\n175m / 191yds / 50g) \r\napprox 6 (9, 12) balls of yarn for the sweater scarf. approx 1110 (1550, 2175)yds.\r\ncrochet hook 4.5mm (g+) or the size that meets the gauge for the pattern, plus a 4mm hook if desired for tighter ribbing.\r\nyarn needle\r\nscissors\r\nstitch markers\r\n\r\npattern includes:\r\ndetailed instructions over 12 page ebook\r\nstitch guide\r\nsizing chart/schematic\r\nstep by step stitch tutorial\r\ncolour inspiration page\r\nfull video tutorial\r\ncustomisation guide\r\n\r\nideal for:\r\na wedding dress shawl\r\nthrowing on over jeans or a dress for a relaxed outfit too!\r\n\r\ninstant download: start crocheting your own sweater scarf with sleeves today! purchase includes immediate access to the 12-page pdf pattern in us crochet terms.\r\n\r\ngauge: \r\n17 sts and 12 rows = 4\" by 4\"\r\n\r\ndiscover a quick and easy crochet wrap pattern that you'll love to create, featuring stunning texture and a flattering design perfect for everyone. \r\n\r\nneed help?\r\nwe're here for you! contact us anytime for pattern support or questions.\r\n\r\nnote:\r\nthis listing is for a digital download pdf pattern, not the finished item. due to the nature of digital downloads, no refunds will be issued.\r\n\r\n© 2024 hanjan crochet ltd. all rights reserved. this pattern and its content are protected by copyright laws. no part of this pattern may be reproduced, distributed, or transmitted in any form or by any means, including photocopying, recording, or other electronic or mechanical methods, without the prior written permission of hanjan crochet ltd, except in the case of brief quotations embodied in critical reviews and certain other noncommercial uses permitted by copyright law.\r\n\r\nthis pattern is for personal use only. it may not be used for commercial purposes without the express permission of hanjan crochet ltd. finished items made from this pattern may be sold in small quantities with credit given to hanjan crochet ltd for the design.\r\n\r\nthank you for respecting the hard work and dedication that went into creating this pattern.\r\n\r\n- technical information\r\n\r\nfile format: this crochet pattern is provided as a digital pdf file only; no physical copy of the pattern or finished item will be supplied. by purchasing and downloading this pattern, you agree to the following below.\r\n\r\nfile size: under 20mb.\r\n\r\ndevice/software compatibility: compatible with devices supporting pdf readers such as adobe acrobat on smartphones, tablets, and computers.\r\n\r\ninternet requirements: an internet connection is needed for downloading the file after purchase.\r\n\r\nusage instructions: download the pdf file from the confirmation email or your account’s download section.\r\n\r\n\r\n- usage instructions\r\n\r\ncomplete your purchase on this platform.\r\n\r\ndownload the pdf file from the confirmation email or your account’s download section.\r\n\r\nopen the file on any pdf-compatible device and follow the pattern instructions.\r\n\r\nrequired tools: see materials needed.\r\n\r\n\r\n- safety and compliance\r\n\r\ncompliance: this pattern complies with the general product safety regulation (gpsr) and other applicable eu directives.\r\n\r\nprecautions:\r\nnot suitable for children under 16 without adult supervision.\r\nensure your device can open pdf files before purchase.\r\n\r\ndisclaimer: this product is for educational and personal use only.\r\n\r\n\r\n\r\n- refund policy\r\n\r\nthis listing is for a digital download pdf pattern, not the finished item. due to the nature of digital downloads, no refunds will be issued. please review all product details before purchase.\r\n\r\ndisclaimer for use: this pattern is provided \"as is\" without any guarantees or warranty. in connection with the use of the pattern, the designer makes no warranties of any kind, either express or implied, including but not limited to warranties of merchantability, non-infringement, or fitness for a particular purpose. the designer is not liable for any damages, including but not limited to direct, indirect, incidental, or consequential damages, arising from the use or inability to use the pattern.\r\n\r\n\r\n- updates and maintenance\r\n\r\nincludes free updates for any corrections or clarifications.\r\n\r\nupdates will be sent via email or can be downloaded from your account.\r\n\r\n- legal and contact information\r\n\r\nbusiness name: hanjan crochet ltd.\r\nbusiness address: 61, bridge street, kington, hr5 3dj.\r\nprivacy policy: https://www.hanjancrochet.com/privacy-policy/\r\neu compliance responsible person (for authorities only): eucomply oü, parnu mnt 139b-14, 11317, tallinn, estonia. hello [at] eucompliancepartner.com \r\n\r\n"
}