{
  "id": 1280907,
  "name": "Fisherman Beanie",
  "permalink": "fisherman-beanie-2",
  "url": "https://www.ravelry.com/patterns/library/fisherman-beanie-2",
  "external_url": "https://pukapuka.pl/fisherman-beanie-free-crochet-pattern/",
  "designer_name": "Maria Jęczmyk",
  "project_type": "Hat",
  "fiber_art": "Crochet",
  "yarn_weight": "DK",
  "materials": [
    {
      "fiber": "DROPS Lima",
      "pct": null
    }
  ],
  "stitches_used": [
    "Double crochet (dc)",
    "Half double crochet (hdc)",
    "Treble crochet (tr)"
  ],
  "techniques_used": [
    "Seamed",
    "Written"
  ],
  "hook_sizes_mm": [
    4.0
  ],
  "needle_sizes_mm": [],
  "published": "2022/10/01",
  "sizes_available": "55-58 cm",
  "rating_average": 5.0,
  "rating_count": 11,
  "difficulty_average": 2.090909090909091,
  "favorites_count": 685,
  "projects_count": 71,
  "free_ravelry_download": false,
  "download_url": "http://www.ravelry.com/purchase/pukapuka/812112"
}