{
  "id": 1349082,
  "name": "Lovina pannebånd",
  "permalink": "lovina-panneband",
  "url": "https://www.ravelry.com/patterns/library/lovina-panneband",
  "external_url": "",
  "designer_name": "Tonje Schjefstad",
  "project_type": "Hat",
  "fiber_art": "Knitting",
  "yarn_weight": "Fingering",
  "materials": [
    {
      "fiber": "Sunday",
      "pct": null
    },
    {
      "fiber": "Tynn Silk Mohair",
      "pct": null
    }
  ],
  "stitches_used": [
    "Treble crochet (tr)"
  ],
  "techniques_used": [],
  "hook_sizes_mm": [],
  "needle_sizes_mm": [
    3.5
  ],
  "published": "2023/07/01",
  "sizes_available": "One size",
  "rating_average": 5.0,
  "rating_count": 13,
  "difficulty_average": 2.4615384615384617,
  "favorites_count": 1082,
  "projects_count": 50,
  "free_ravelry_download": true,
  "download_url": "http://www.ravelry.com/dls/80595/866646",
  "pdf": {
    "filename": "1349082.pdf",
    "path": "C:\\Users\\PSLAVCHE\\Documents\\University\\AI\\CrochetAndKnittingSearchEngine\\pdfs\\1349082.pdf",
    "url": "https://pdf.ravelrycache.com/tonjeknitwear/1690865/Lovina_panneband.pdf?AWSAccessKeyId=AKIAJNNSUP6J3RN4WZYQ&Expires=1768481574&Signature=M1UbV%2FpOxlOCt0sgUBWUtzmtcrE%3D&key_expires=1768481574&key=1z5KusO0l5BxLwiZLywloA",
    "size_bytes": 904639
  }
}