{
  "id": 1327443,
  "name": "mini unicorn",
  "permalink": "mini-unicorn-7",
  "url": "https://www.ravelry.com/patterns/library/mini-unicorn-7",
  "external_url": "https://youtu.be/X3pP8fJH3b4",
  "designer_name": "skein spider",
  "project_type": "toys",
  "fiber_art": "crochet",
  "yarn_weight": "dk",
  "materials": [
    {
      "fiber": "Acrylic (Acrylic)",
      "pct": 100.0
    }
  ],
  "stitches_used": [
    "single crochet (sc)"
  ],
  "techniques_used": [
    "in the round"
  ],
  "hook_sizes_mm": [
    3.5
  ],
  "needle_sizes_mm": [],
  "published": "2023/03/01",
  "sizes_available": "",
  "rating_average": 4.666666666666667,
  "rating_count": 3,
  "difficulty_average": 2.0,
  "favorites_count": 243,
  "projects_count": 15,
  "free_ravelry_download": false,
  "download_url": "https://youtu.be/X3pP8fJH3b4",
  "notes": "a chonky little unicorn!\r\n\r\nthe pattern and tutorial is available here:\r\nhttps://youtu.be/x3pp8fjh3b4\r\n\r\npattern details:\r\nhook size: 3.5mm\r\nyarn: 8ply\r\nterms: us\r\ndifficulty: advanced beginner\r\nfinished size: 8cm\r\n\r\nmaterials & supplies:\r\nto make this pattern you will need:\r\n• yarn\r\n• scissors\r\n• stitch markers\r\n• needle\r\n• pins\r\n• stuffing\r\n• 9mm safety eyes"
}