{
  "id": 7366229,
  "name": "mosaic gingerbread blanket",
  "permalink": "mosaic-gingerbread-blanket",
  "url": "https://www.ravelry.com/patterns/library/mosaic-gingerbread-blanket",
  "external_url": "https://juniperandoakes.com/blog/mosaic-gingerbread-blanket-crochet-along",
  "designer_name": "erin toews",
  "project_type": "blanket",
  "fiber_art": "crochet",
  "yarn_weight": "worsted",
  "materials": [
    {
      "fiber": "Acrylic (Acrylic)",
      "pct": 80.0
    },
    {
      "fiber": "Wool (Wool)",
      "pct": 20.0
    }
  ],
  "stitches_used": [
    "single crochet (sc)",
    "treble crochet (tr)"
  ],
  "techniques_used": [
    "bottom-up",
    "charted",
    "mosaic",
    "written"
  ],
  "hook_sizes_mm": [
    4.0
  ],
  "needle_sizes_mm": [],
  "published": "2024/08/01",
  "sizes_available": "one size, more size details in notes",
  "rating_average": 4.8,
  "rating_count": 20,
  "difficulty_average": 3.8947368421052633,
  "favorites_count": 2342,
  "projects_count": 94,
  "free_ravelry_download": false,
  "download_url": "http://www.ravelry.com/purchase/juniper--oakes/949409",
  "notes": "**free crochetalong fall 2024!** pattern is being released for free [on my ad-supported website][1] bit by bit from september 16-december 2. (full pattern available to purchase right away). \r\n\r\npurchasing the pattern will give you english instructions for both:\r\n* overlay mosaic\r\n* reversible using negative stitch\r\n\r\n***spanish** version of the regular overlay mosaic crochet pattern is also included.*\r\n\r\ncreate holiday magic with the **mosaic gingerbread blanket**—a festive crochet pattern featuring gingerbread men, houses, and candy canes. this overlay mosaic design adds a warm, cozy touch to your winter decor and can be crafted in the traditional method or made reversible using the negative stitch.\r\n  \r\nperfect for snuggling by the fire, this pattern is released weekly for free on the juniper & oakes website, with an option to purchase the full pdf. enhance your holiday decor or gift it to loved ones—this timeless blanket is a seasonal treasure you’ll cherish for years to come. \r\n\r\n[the pattern is also free on my ad-supported website, as a 12-week crochetalong with sections released week by week.][2]\r\n& [purchasing the full pattern on my website will save you a couple dollars.][3]\r\n  \r\nget ready to embark on a crochet adventure with the mosaic gingerbread blanket pattern! this intermediate-level crochet throw pattern features a mesmerizing mosaic design that will captivate your imagination. crafted using 4000-5000 yards of knit picks' mighty stitch worsted weight yarn, this blanket showcases the perfect blend of softness and durability.\r\n  \r\nthe pattern includes detailed written instructions, a photo tutorial, and a video tutorial to guide you through each step of the process. with a gauge of 18 stitches and 22 rows in a 4-inch mosaic swatch on the ws, you'll achieve a beautifully textured finish.\r\n  \r\nwhether you're a seasoned crocheter or looking to expand your skills, this pattern offers a rewarding challenge that will result in a stunning rectangular blanket. customize the size to fit your preference and create a cozy masterpiece that will be cherished for years to come.\r\n  \r\n**unique features-**\r\n\\- intricate crochet mosaic design\r\n\\- detailed written, photo, and video tutorials\r\n\\- customizable size options\r\n  \r\n  \r\n**materials needed-**\r\n\\- yarn: [knit picks mighty stitch worsted][4] (*yardage is for reversible pattern. will need approximately 25% less for regular overlay*)\r\n• color a (cream) - 2325 yards/12 skeins\r\n• color b (palomino) - 1290 yards/7 skeins\r\n• color c (love letter) - 975 yards/5 skeins\r\n\\- crochet hook: size 4.0 mm (us size g/6)\r\n\\- stitch markers (optional)\r\n\\- yarn needle\r\n\\- scissors\r\n\\- [snips holder][5]\r\n\\- gauges:\r\n18 stitches x 22 rows = 4 inches in mosaic swatch on the ws\r\n18 stitches and 22 rows = 4 inches in mosaic swatch on the ws\r\n\r\n[join the ravelry group][6]\r\n[join the facebook group][7]\r\n\r\n\r\n  [1]: https://juniperandoakes.com/blog/mosaic-gingerbread-blanket-crochet-along\r\n  [2]: https://juniperandoakes.com/blog/mosaic-gingerbread-blanket-crochet-along\r\n  [3]: https://juniperandoakes.thrivecart.com/mosaic-gingerbread-crochetalong/?ref=ravelry\r\n  [4]: https://shrsl.com/4ne6e\r\n  [5]: https://www.sewtites.com/products/sewtites-wearable-magnetic-straight-pin-snips-holder?ref=juniperandoakes\r\n  [6]: https://www.ravelry.com/groups/mosaic-gingerbread-blanket-crochetalong\r\n  [7]: https://www.facebook.com/groups/juniperandoakes"
}