{
  "id": 1313229,
  "name": "mr. ruesselo the elephant",
  "permalink": "mr-ruesselo-the-elephant",
  "url": "https://www.ravelry.com/patterns/library/mr-ruesselo-the-elephant",
  "external_url": "",
  "designer_name": "svitlana kondratova",
  "project_type": "toys",
  "fiber_art": "knitting",
  "yarn_weight": "sport",
  "materials": [
    {
      "fiber": "Cotton (Cotton)",
      "pct": 50.0
    },
    {
      "fiber": "Egyptian (Cotton)",
      "pct": 50.0
    }
  ],
  "stitches_used": [
    "single crochet (sc)",
    "treble crochet (tr)"
  ],
  "techniques_used": [
    "in the round",
    "seamless",
    "written"
  ],
  "hook_sizes_mm": [],
  "needle_sizes_mm": [
    2.0
  ],
  "published": "2023/02/01",
  "sizes_available": "",
  "rating_average": 4.64,
  "rating_count": 25,
  "difficulty_average": 4.24,
  "favorites_count": 2844,
  "projects_count": 108,
  "free_ravelry_download": true,
  "download_url": "http://www.ravelry.com/dls/94300/838865",
  "notes": "this is a knitting pattern of an elephant named mr. ruesselo. it includes a material list, abbreviations, row by row instructions, and photos.\r\n\r\nknitted in the round using the magic loop method. legs and trunk are attached as you knit, and stitches for the ears are picked up and knitted flat. no sewing is required.\r\n\r\n**skill level:** advanced beginner.\r\n\r\n**used techniques**\r\n* pinhole cast-on \r\n* turkish cast-on\r\n* backwards loop cast-on\r\n* knitting flat and in the round\r\n* slipping and purling stitches\r\n* increases (make one left, make one right)\r\n* decreases (knit two together, slip slip knit)\r\n* picking up stitches\r\n* three-needle bind-off\r\n* binding off\r\n\r\n**materials required** \r\n* sport yarn (45-50g). \r\n* 2 mm circular knitting needles\r\n* 2 mm two double-pointed needles\r\n* 3 mm crochet hook\r\n* darning needle\r\n* stuffing\r\n* stitch markers\r\n* scrap yarn to keep stitches on hold\r\n* scrap yarn in black for embroidery\r\n\r\nyarn used for the yellow one: drops loves you 7 #28 (15g); drops safran #66 (30g)\r\n\r\n**size**\r\napproximately 23cm x 16cm.\r\n\r\n**errata**\r\npage 4: put all leg sts **on circular needles** (not dpns).\r\npage 5: body&head r43 **only one repeat**\r\npage 6: body&head r58 **2 repeats** of the sequence between the square brackets\r\n\r\nyou may sell the finished toy, provided you give the credit to svitlana kondratova as the designer.\r\n\r\nyou may not sell or share the pattern.\r\n\r\nplease don’t forget to tag your creations on instagram with @im_strickfieber #mrruesselotheelephant\r\n\r\nif you have any questions please do not hesitate to contact me.\r\n\r\nif you want to thank me, please consider donating a little to my homeland ukraine. on the page of [friends for ukraine][1] you can find some volunteers, who demonstrate heroic humanitarian work, providing people and animals with food and medicines. every donation makes a difference.\r\n-------------------------------\r\n\r\n\r\n  [1]: https://friendsforukraine.de/",
  "pdf": {
    "filename": "1313229.pdf",
    "path": "C:\\Users\\PSLAVCHE\\Documents\\University\\AI\\CrochetAndKnittingSearchEngine\\pdfs\\1313229.pdf",
    "url": "https://pdf.ravelrycache.com/ImStrickfieber/1626538/Mr._Ruesselo_the_Elephant_ENG.pdf?AWSAccessKeyId=AKIAJNNSUP6J3RN4WZYQ&Expires=1770434783&Signature=ppucN%2Fv%2F3A%2BOTd2OvgUMAc9VS2M%3D&key_expires=1770434783&key=7g_YbvujB0s-kz0u93qyQA",
    "size_bytes": 20593874
  }
}