{
  "id": 753406,
  "name": "Piitu Mitts",
  "permalink": "piitu-mitts",
  "url": "https://www.ravelry.com/patterns/library/piitu-mitts",
  "external_url": "",
  "designer_name": "Heidi Alander",
  "project_type": "Mittens/Gloves",
  "fiber_art": "Knitting",
  "yarn_weight": "Fingering",
  "materials": [
    {
      "fiber": "Casbah",
      "pct": null
    }
  ],
  "stitches_used": [
    "Lace",
    "Stockinette stitch"
  ],
  "techniques_used": [
    "Charted",
    "In the round",
    "Lace",
    "Seamless"
  ],
  "hook_sizes_mm": [],
  "needle_sizes_mm": [
    3.0
  ],
  "published": "2017/06/01",
  "sizes_available": "women's",
  "rating_average": 4.826086956521739,
  "rating_count": 138,
  "difficulty_average": 2.5671641791044775,
  "favorites_count": 7198,
  "projects_count": 635,
  "free_ravelry_download": true,
  "download_url": "http://www.ravelry.com/dls/34324/400593"
}