{
  "id": 988296,
  "name": "rainbow granny square sweater",
  "permalink": "rainbow-granny-square-sweater",
  "url": "https://www.ravelry.com/patterns/library/rainbow-granny-square-sweater",
  "external_url": "https://www.hanjancrochet.com/rainbow-granny-square-sweater-pattern/",
  "designer_name": "hannah cross",
  "project_type": "pullover",
  "fiber_art": "crochet",
  "yarn_weight": "dk",
  "materials": [
    {
      "fiber": "Wool (Wool)",
      "pct": 100.0
    }
  ],
  "stitches_used": [
    "cable",
    "granny",
    "ribbing",
    "single crochet (sc)",
    "treble crochet (tr)"
  ],
  "techniques_used": [
    "cables",
    "written"
  ],
  "hook_sizes_mm": [
    4.5
  ],
  "needle_sizes_mm": [],
  "published": "2025/03/01",
  "sizes_available": "81-117cm (32-46in)",
  "rating_average": 4.6,
  "rating_count": 15,
  "difficulty_average": 1.8,
  "favorites_count": 4404,
  "projects_count": 92,
  "free_ravelry_download": false,
  "download_url": "http://www.ravelry.com/purchase/hanjan-crochet-designs-by-hannah-cross/701786",
  "notes": "create a retro crochet granny square sweater with our stunning pattern, available in sizes xs to 5xl. this easy design combines the traditional granny square with endless colour options to make it truly yours. make just 4 granny squares then add as much ribbing or length after seaming to suit you!\r\n\r\nthis pattern is suitable for beginners as it includes step-by-step instructions to guide you through the process. the pattern includes sizes ranging from xs-5x to create the perfect fit for yourself or a loved one. you’ll also get access to a step-by-step video on youtube showing you exactly how to create the sweater from start to finish.\r\n\r\n*please note*-- this listing is for a pdf pattern written in english, not a finished product.\r\n\r\npattern features:\r\nadult sizes xs to 5xl (30-62\" chest): ensure the perfect fit for every body type.\r\nskill level: easy\r\nstitch: granny square and stitch\r\ninstant pdf download\r\nwith and without ribbing options\r\nadjustable length and styling options \r\nfull video tutorial (to support written pattern if you are a visual learner)\r\nus crochet terms\r\nuk stitch conversion chart\r\n\r\nwhy you'll love this pattern:\r\nversatile design: customize the length and sleeves to be perfect for your style.\r\ncustomize the styling: with options for a traditional rib edging or a lighter option for summer\r\ndetailed instructions: 13-page pdf in us crochet terms for clear, easy-to-follow guidance.\r\n\r\nmaterials needed:\r\ncategory 3 (dk) yarn (i used prism dk, 100% acrylic, 265m/290yds/100g) \r\napprox 5 (5, 5, 6, 6) (6, 7, 7, 7) balls of yarn for the sweater with sleeves. approx 1200 (1350, 1450, 1560, 1630) (1700, 1810, 1930, 2035)yds.\r\ncrochet hook 4.5mm (g+) or the size that meets the gauge for the pattern.\r\nyarn needle\r\nscissors\r\nstitch markers\r\n\r\npattern includes:\r\ndetailed instructions over 13 page ebook\r\nstitch guide\r\nsizing chart/schematic\r\nstep by step stitch tutorial\r\ncolour inspiration page\r\nfull video tutorial\r\ncustomisation guide\r\n\r\nideal for:\r\ndress up or down for the office or home\r\na beach or holiday top for daytime or evenings\r\na fun summer top that taps into the current granny crochet square trend\r\n\r\ninstant download: start crocheting your own granny stitch top today! purchase includes immediate access to the 13-page pdf pattern in us crochet terms.\r\n\r\ngauge: \r\n4 rounds of granny square = 4\" by 4\"\r\n\r\ndiscover a modern crochet sweater pattern that you'll love to create, featuring fun details and a flattering design perfect for everyone. \r\n\r\nneed help?\r\nwe're here for you! contact us anytime for pattern support or questions.\r\n\r\nnote:\r\nthis listing is for a digital download pdf pattern, not the finished item. due to the nature of digital downloads, no refunds will be issued.\r\n\r\n© 2024 hanjan crochet ltd. all rights reserved. this pattern and its content are protected by copyright laws. no part of this pattern may be reproduced, distributed, or transmitted in any form or by any means, including photocopying, recording, or other electronic or mechanical methods, without the prior written permission of hanjan crochet ltd, except in the case of brief quotations embodied in critical reviews and certain other noncommercial uses permitted by copyright law.\r\n\r\nthis pattern is for personal use only. it may not be used for commercial purposes without the express permission of hanjan crochet ltd. finished items made from this pattern may be sold in small quantities with credit given to hanjan crochet ltd for the design.\r\n\r\nthank you for respecting the hard work and dedication that went into creating this pattern.\r\n\r\n\r\n- technical information\r\n\r\nfile format: this crochet pattern is provided as a digital pdf file only; no physical copy of the pattern or finished item will be supplied. by purchasing and downloading this pattern, you agree to the following below.\r\n\r\nfile size: under 20mb.\r\n\r\ndevice/software compatibility: compatible with devices supporting pdf readers such as adobe acrobat on smartphones, tablets, and computers.\r\n\r\ninternet requirements: an internet connection is needed for downloading the file after purchase.\r\n\r\nusage instructions: download the pdf file from the confirmation email or your account’s download section.\r\n\r\n\r\n- usage instructions\r\n\r\ncomplete your purchase on this platform.\r\n\r\ndownload the pdf file from the confirmation email or your account’s download section.\r\n\r\nopen the file on any pdf-compatible device and follow the pattern instructions.\r\n\r\nrequired tools: see materials needed.\r\n\r\n\r\n- safety and compliance\r\n\r\ncompliance: this pattern complies with the general product safety regulation (gpsr) and other applicable eu directives.\r\n\r\nprecautions:\r\nnot suitable for children under 16 without adult supervision.\r\nensure your device can open pdf files before purchase.\r\n\r\ndisclaimer: this product is for educational and personal use only.\r\n\r\n\r\n\r\n- refund policy\r\n\r\nthis listing is for a digital download pdf pattern, not the finished item. due to the nature of digital downloads, no refunds will be issued. please review all product details before purchase.\r\n\r\ndisclaimer for use: this pattern is provided \"as is\" without any guarantees or warranty. in connection with the use of the pattern, the designer makes no warranties of any kind, either express or implied, including but not limited to warranties of merchantability, non-infringement, or fitness for a particular purpose. the designer is not liable for any damages, including but not limited to direct, indirect, incidental, or consequential damages, arising from the use or inability to use the pattern.\r\n\r\n\r\n- updates and maintenance\r\n\r\nincludes free updates for any corrections or clarifications.\r\n\r\nupdates will be sent via email or can be downloaded from your account.\r\n\r\n- legal and contact information\r\n\r\nbusiness name: hanjan crochet ltd.\r\nbusiness address: 61, bridge street, kington, hr5 3dj.\r\nprivacy policy: https://www.hanjancrochet.com/privacy-policy/\r\neu compliance responsible person (for authorities only): eucomply oü, parnu mnt 139b-14, 11317, tallinn, estonia. hello [at] eucompliancepartner.com \r\n\r\n\r\n\r\n  [1]: https://www.hanjancrochet.com/rainbow-granny-square-sweater-pattern/\r\n  [2]: https://view.flodesk.com/pages/5f205d6c6844c60026e8f259"
}