{
  "id": 7344101,
  "name": "riverbed cardigan",
  "permalink": "riverbed-cardigan",
  "url": "https://www.ravelry.com/patterns/library/riverbed-cardigan",
  "external_url": "https://www.cjdesignblog.com/riverbed-cardigan",
  "designer_name": "cj design",
  "project_type": "cardigan",
  "fiber_art": "crochet",
  "yarn_weight": "aran",
  "materials": [
    {
      "fiber": "Acrylic (Acrylic)",
      "pct": 93.3
    },
    {
      "fiber": "Wool (Wool)",
      "pct": 6.7
    }
  ],
  "stitches_used": [
    "double crochet (dc)",
    "treble crochet (tr)"
  ],
  "techniques_used": [
    "seamed",
    "worked flat"
  ],
  "hook_sizes_mm": [
    5.5
  ],
  "needle_sizes_mm": [],
  "published": "2024/05/01",
  "sizes_available": "xs to 4 xl",
  "rating_average": 4.5,
  "rating_count": 12,
  "difficulty_average": 3.1818181818181817,
  "favorites_count": 1420,
  "projects_count": 44,
  "free_ravelry_download": false,
  "download_url": "http://www.ravelry.com/purchase/cj-design-designs/932219",
  "notes": "you will receive a pdf file with step-by-step instructions on how to make the riverbed cardigan. \r\n\r\nsizes: xs to 4 xl\r\nfit: oversized cardigan with 14\" positive ease on the bust circumference.\r\nskill level: confident beginner\r\nyarn: colour theory by lion brand yarn, worsted weight #4\r\nconstruction: this pattern is worked flat, making panels, so there are no increases and decreases.\r\nthe pattern uses standard american terms\r\n\r\ni would love to see your finished products\r\ntag me on instagram @cj.dsgn and use the hashtag #riverbedcardigan\r\n\r\nrefund\r\nthere are no refunds on patterns\r\n\r\nplease note that this pattern can be found for free, with ads on my blog at cjdesignblog.com"
}