{
  "id": 1325228,
  "name": "simply a slouchy beanie",
  "permalink": "simply-a-slouchy-beanie",
  "url": "https://www.ravelry.com/patterns/library/simply-a-slouchy-beanie",
  "external_url": "",
  "designer_name": "joan rowe",
  "project_type": "child",
  "fiber_art": "knitting",
  "yarn_weight": "dk",
  "materials": [
    {
      "fiber": "Merino (Merino)",
      "pct": 70.0
    },
    {
      "fiber": "Cashmere goat (Cashmere)",
      "pct": 20.0
    },
    {
      "fiber": "Nylon / Polyamide (Nylon)",
      "pct": 10.0
    }
  ],
  "stitches_used": [
    "stockinette stitch",
    "treble crochet (tr)"
  ],
  "techniques_used": [
    "bottom-up",
    "in the round",
    "seamless",
    "written"
  ],
  "hook_sizes_mm": [],
  "needle_sizes_mm": [
    4.0
  ],
  "published": "2023/04/01",
  "sizes_available": "head sizes 18” (46cm), 21” (53cm), 22\" (56cm) and 23” (58cm) ",
  "rating_average": 4.5,
  "rating_count": 14,
  "difficulty_average": 2.1875,
  "favorites_count": 1059,
  "projects_count": 65,
  "free_ravelry_download": true,
  "download_url": "http://www.ravelry.com/dls/33099/848165",
  "notes": "this is a very simple, slouchy beanie which will beautifully show off the color changes in hand painted yarns. \r\nit is knitted in the round from the bottom up. \r\na beginner level knitter should do fine with this pattern.\r\n\r\ninstructions are given for head sizes 18” (46 cm), 21” (53 cm), 22” (56 cm) and 23” (58 cm). these correspond to child, small, medium and large adult sizes.\r\n\r\nthe beanie is knitted with sport weight or light dk yarn. you may use any sport or light dk weight yarn, but the yarn used in the hat pictured is dream in color cosette.\r\n\r\namount of yarn needed: (100, 125, 150, 175) yds / (90, 114, 136, 160) m \r\n\r\ngauge: 22 sts and 28 rows/4” (10 cm) in unblocked stockinette.\r\n",
  "pdf": {
    "filename": "1325228.pdf",
    "path": "C:\\Users\\PSLAVCHE\\Documents\\University\\AI\\CrochetAndKnittingSearchEngine\\pdfs\\1325228.pdf",
    "url": "https://pdf.ravelrycache.com/joansgarden/1647294/Simply_a_Slouchy_Beanie.pdf?AWSAccessKeyId=AKIAJNNSUP6J3RN4WZYQ&Expires=1770440748&Signature=YEN0mcl1xgpyqv0%2BVqcHiIUn%2FMU%3D&key_expires=1770440748&key=rTGAceMVXRZWGjAy-oMYEA",
    "size_bytes": 275634
  }
}