{
  "id": 7483299,
  "name": "smallidays",
  "permalink": "smallidays",
  "url": "https://www.ravelry.com/patterns/library/smallidays",
  "external_url": "",
  "designer_name": "stephanie lotven",
  "project_type": "home",
  "fiber_art": "knitting",
  "yarn_weight": "dk",
  "materials": [
    {
      "fiber": "Merino (Merino)",
      "pct": 75.0
    },
    {
      "fiber": "Nylon / Polyamide (Nylon)",
      "pct": 25.0
    }
  ],
  "stitches_used": [
    "garter stitch",
    "lace",
    "ribbing",
    "single crochet (sc)",
    "stockinette stitch",
    "treble crochet (tr)"
  ],
  "techniques_used": [
    "blocking",
    "in the round",
    "lace",
    "seamless",
    "written"
  ],
  "hook_sizes_mm": [],
  "needle_sizes_mm": [
    3.75
  ],
  "published": "2025/12/01",
  "sizes_available": "ornament size",
  "rating_average": 5.0,
  "rating_count": 6,
  "difficulty_average": 2.6666666666666665,
  "favorites_count": 1105,
  "projects_count": 41,
  "free_ravelry_download": true,
  "download_url": "http://www.ravelry.com/dls/37638/1041408",
  "notes": "> **buy 3, get 1 free! place 4 of my patterns in your cart and the 4th\r\n> (least expensive) will be free. no\r\n> coupon code needed.**\r\n> \r\n> **let's stay in touch!** \r\n> [subscribe to my\r\n> newsletter](https://www.tellybeanknits.com/newsletter-sign-up)\r\n> &#9829; [follow me on instagram\r\n> @tellybeanknits]\r\n\r\n*since the yarn used for this pattern is still a secret, all the photos in this pattern are currently in black & white. an updated, full-color version of this pattern will be released at the end of december.*\r\n\r\nsmallidays is a charming knitted ornament collection that brings extra warmth and whimsy to the holiday season. each tiny design is quick, festive, and perfect for turning leftover bits of scrap yarn into something magical. it’s the perfect project for working through an advent yarn kit, letting you savor a new color each day while filling your tree with handmade cheer. you can even string these ornaments together to create a cheerful advent garland. with every stitch, smallidays captures the cozy spirit of christmas in adorable, miniature form. \r\n\r\nthis pattern includes a miniature sweater, hat, mitten, and scarf pattern! the pattern also includes a quick photo tutorial for adding a tassel to your hat and fringe to your scarf.\r\n\r\nto create this little ornament collection, i worked in collaboration with [emma's yarn](https://emmasyarn.com) using the [smallidays 2025 - simply spectacular dk kit](https://emmasyarn.com/collections/2025-smalliday-set), but you do not need an advent kit to enjoy this pattern. the smallidays ornaments are the perfect project for stash diving! \r\n\r\n\r\n**sizes**\r\none size: teensy weensy ornament size\r\nsee finished dimensions below.\r\n\r\n**yarn**  \t\r\ndk weight yarn\r\nemma’s yarn simply spectacular dk smalls (75% superwash merino wool & 25% nylon, 50 yards / 0.7 oz [46 meters / 20 grams) \r\n\r\nsample shown in “2025 smallidays dk advent kit” \r\n\r\nmini hat: 25 yards / 23 meters\r\nmini sweater: 45 yards / 41 meters\r\nmini mitten: 20 yards / 18 meters\r\nmini scarf: 15 yards / 14 meters\r\n\r\n\r\n\r\n**finished dimensions**\r\n*mini hat*\r\nwidth (flat without tassel): 4 inches / 10 cm\r\nlength: 3.25 inches / 8 cm\r\n\r\n*mini sweater*\r\nchest width (flat):  3.5 inches / 9 cm\r\nlength: 4 inches / 10 cm\r\n\r\n*mini mitten*\r\npalm width (flat): 2.25 inches / 5.5 cm\r\nlength: 3.25 inches / 8 cm\r\n\r\n*mini scarf*\r\nwidth: 1.5 inches [3.5 cm]\r\nlength (without fringe): 7.5 inches [19 cm]\r\n\r\n**needles**\r\nus 5 (3.75mm) or as required to meet gauge dpns or preferred needle size for small circumference knitting\r\n\r\n**gauge**\r\n*for the hat, mitten, and sweater*\r\n22 sts & 32 rounds = 4 inches [10cm] in stockinette in the round after blocking\r\n\r\n*for scarf*\r\n22 sts & 40 rows = 4 inches [10cm] in garter stitch after blocking\r\n\r\n**tools**\t\t \r\n8 stitch markers for the sweater / 3 stitch markers for the mini mitten / 1 stitch marker for the mini hat, scrap yarn, tapestry needle, & crochet hook for adding tassels to the scarf\r\n\r\n**skills**\r\nknitting flat, knitting in the round, increases, decreases, ribbing\r\n",
  "pdf": {
    "filename": "7483299.pdf",
    "path": "C:\\Users\\PSLAVCHE\\Documents\\University\\AI\\CrochetAndKnittingSearchEngine\\pdfs\\7483299.pdf",
    "url": "https://pdf.ravelrycache.com/needlesandyarn/2098238/Smallidays_Ornaments.pdf?AWSAccessKeyId=AKIAJNNSUP6J3RN4WZYQ&Expires=1770441241&Signature=yIUJLSILRJgWNAfEFPrfJmmlHHE%3D&key_expires=1770441241&key=a1wN2xiufMaFdNyHjT_TQQ",
    "size_bytes": 12383049
  }
}