{
  "id": 605915,
  "name": "spice of life blanket",
  "permalink": "spice-of-life-blanket",
  "url": "https://www.ravelry.com/patterns/library/spice-of-life-blanket",
  "external_url": "http://www.cherryheart.co.uk/2016/03/spice-of-life-crochet-along-blanket.html",
  "designer_name": "sandra paul",
  "project_type": "blanket",
  "fiber_art": "crochet",
  "yarn_weight": "dk",
  "materials": [
    {
      "fiber": "Acrylic (Acrylic)",
      "pct": 50.0
    },
    {
      "fiber": "Nylon / Polyamide (Nylon)",
      "pct": 50.0
    }
  ],
  "stitches_used": [
    "double crochet (dc)",
    "treble crochet (tr)"
  ],
  "techniques_used": [
    "written"
  ],
  "hook_sizes_mm": [
    4.0
  ],
  "needle_sizes_mm": [],
  "published": "2015/09/01",
  "sizes_available": "one size: 106 x 138 cm (42 x 54\")",
  "rating_average": 4.747685185185185,
  "rating_count": 432,
  "difficulty_average": 2.9263657957244655,
  "favorites_count": 20225,
  "projects_count": 1531,
  "free_ravelry_download": true,
  "download_url": "http://www.ravelry.com/dls/6019/290893",
  "notes": "<big>spice of life crochet along</big> \r\n**#spiceoflifecal**\r\n\r\nthis spice of life blanket pattern was originally released in parts for the cherry heart and black sheep wools cal.\r\n\r\n> now available as a pdf with bonus content: **[spice of\r\n> life remixed][3]**\r\n\r\nthis is the first of the 'spicy' cal blankets, to find the second blanket, see '[a spicier life][1]'.\r\n\r\nskill - easy/intermediate \r\nthis pattern is intended to help someone who has learnt the basics of crochet and is now looking to move increase their crochet confidence. this pattern starts with the basics and progresses through to intermediate stitches and combinations. it is a great way to get used to working from written patterns.\r\n\r\nyarn \r\na total of 2,380m/2,600 yards of dk weight yarn in 13 different colours as follows:\r\n\r\nyou’ll need 180 yards (approx) in 13 colours for the main blanket \r\nyou’ll also need an extra 180 yards (approx) in your chosen border colour \r\n(based on the original rico yarn pack.)\r\n\r\n[cherry heart boutique at black sheep wools][2]\r\n\r\nfor more yarn details see the link below.\r\n\r\n\r\nfree pattern includes:\r\n- a full written pattern with clear instructions in uk or us terms\r\n- social media and spice of life facebook group links\r\n- links to spice of life page for original blog post tips\r\n\r\nsee **[spice of life remixed for the full pdf version][3]**, with more help and bonus content.\r\n\r\n**cherry heart’s cozy corner** \r\nplease come and join the [cherry heart group][4]. watch podcasts, join crochet/knit alongs, share your projects and enjoy yarny chit chat.\r\n\r\ni love to see your projects… #spiceoflifeblanket #cherryheart\r\n\r\n**translations**\r\ndutch - many thanks to iris van meer of een mooi gebaar (linked below)\r\nfrench - many thanks to stella of [mes petit (ré)créations][5]\r\n\r\n\r\n  [1]: https://www.ravelry.com/patterns/library/a-spicier-life-blanket\r\n  [2]: https://www.blacksheepwools.com/collections/black-sheep-boutique-cherry-heart\r\n  [3]: https://www.ravelry.com/patterns/library/spice-of-life-remixed\r\n  [4]: https://www.ravelry.com/groups/cherry-hearts-cozy-corner\r\n  [5]: https://mespetitesrecreations.wordpress.com"
}