{
  "id": 1341574,
  "name": "Sunflower Coasters in Basket",
  "permalink": "sunflower-coasters-in-basket",
  "url": "https://www.ravelry.com/patterns/library/sunflower-coasters-in-basket",
  "external_url": "https://www.youtube.com/watch?v=GV6NmdSPI_8",
  "designer_name": "Papari Sharma",
  "project_type": "Home",
  "fiber_art": "Crochet",
  "yarn_weight": "DK",
  "materials": [
    {
      "fiber": "Soft Cotton",
      "pct": null
    }
  ],
  "stitches_used": [
    "Single crochet (sc)",
    "Treble crochet (tr)"
  ],
  "techniques_used": [
    "In the round",
    "Written"
  ],
  "hook_sizes_mm": [
    3.5
  ],
  "needle_sizes_mm": [],
  "published": "2023/06/01",
  "sizes_available": "",
  "rating_average": 4.7272727272727275,
  "rating_count": 11,
  "difficulty_average": 2.1,
  "favorites_count": 2687,
  "projects_count": 61,
  "free_ravelry_download": false,
  "download_url": "http://www.ravelry.com/purchase/make-it-yourself-by-papari/860773"
}