{
  "id": 7475580,
  "name": "the bookstore headband",
  "permalink": "the-bookstore-headband",
  "url": "https://www.ravelry.com/patterns/library/the-bookstore-headband",
  "external_url": "https://www.sprucehillknits.com/blog/pattern-the-bookstore-headband/",
  "designer_name": "spruce hill knits",
  "project_type": "hat",
  "fiber_art": "knitting",
  "yarn_weight": "worsted",
  "materials": [
    {
      "fiber": "Wool (Wool)",
      "pct": 100.0
    }
  ],
  "stitches_used": [
    "single crochet (sc)"
  ],
  "techniques_used": [],
  "hook_sizes_mm": [],
  "needle_sizes_mm": [
    5.0
  ],
  "published": "2025/11/01",
  "sizes_available": "",
  "rating_average": 5.0,
  "rating_count": 3,
  "difficulty_average": 0,
  "favorites_count": 382,
  "projects_count": 11,
  "free_ravelry_download": false,
  "download_url": "https://www.sprucehillknits.com/blog/pattern-the-bookstore-headband/",
  "notes": "ttis pattern is designed to complement the bookstore scarf, also available on my blog. www.sprucehillknits.com"
}