{
  "id": 7442025,
  "name": "The Liliana Bandana",
  "permalink": "the-liliana-bandana",
  "url": "https://www.ravelry.com/patterns/library/the-liliana-bandana",
  "external_url": "https://www.cutiepiecrochet.com/post/the-liliana-bandana",
  "designer_name": "Cutiepie Crochet",
  "project_type": "Hat",
  "fiber_art": "Crochet",
  "yarn_weight": "Worsted",
  "materials": [],
  "stitches_used": [
    "Double crochet (dc)",
    "Single crochet (sc)",
    "Slip stitch (sl st)",
    "Treble crochet (tr)"
  ],
  "techniques_used": [
    "Written"
  ],
  "hook_sizes_mm": [
    5.0
  ],
  "needle_sizes_mm": [],
  "published": "2025/06/01",
  "sizes_available": "",
  "rating_average": 0,
  "rating_count": null,
  "difficulty_average": 0,
  "favorites_count": 189,
  "projects_count": 9,
  "free_ravelry_download": false,
  "download_url": "https://www.cutiepiecrochet.com/post/the-liliana-bandana"
}