{
  "id": 1336496,
  "name": "Mosaic Goldfish",
  "permalink": "mosaic-goldfish",
  "url": "https://www.sweetsofties.com/2023/05/mosaic-goldfish.html",
  "designer_name": null,
  "project_type": "Toys",
  "fiber_art": "Crochet",
  "yarn_weight": "Fingering",
  "materials": [],
  "stitches_used": [],
  "hook_sizes_mm": [
    2.25
  ],
  "needle_sizes_mm": [],
  "published": "2023/05/01",
  "sizes_available": "See description below",
  "rating_average": 4.804878048780488,
  "rating_count": 41,
  "difficulty_average": 3.0,
  "favorites_count": 11281,
  "projects_count": 144
}