{
  "id": 7370895,
  "name": "Wheat Stitch™ Pumpkin Spice Crochet Trio",
  "permalink": "wheat-stitchtm-pumpkin-spice-crochet-trio",
  "url": "https://www.ravelry.com/patterns/library/wheat-stitchtm-pumpkin-spice-crochet-trio",
  "external_url": "https://brianakdesigns.com/pumpkin-spice-crochet-pumpkin-trio/",
  "designer_name": "Briana K Designs",
  "project_type": "Home",
  "fiber_art": "Crochet",
  "yarn_weight": "Worsted",
  "materials": [
    {
      "fiber": "Wool of the Andes Tweed Worsted",
      "pct": null
    },
    {
      "fiber": "Wool of the Andes Worsted",
      "pct": null
    }
  ],
  "stitches_used": [
    "Single crochet (sc)",
    "Treble crochet (tr)"
  ],
  "techniques_used": [
    "Seamed"
  ],
  "hook_sizes_mm": [
    5.0
  ],
  "needle_sizes_mm": [],
  "published": "2025/08/01",
  "sizes_available": "Three Sizes - Small, Medium, Large",
  "rating_average": 4.921568627450981,
  "rating_count": 102,
  "difficulty_average": 2.9393939393939394,
  "favorites_count": 6951,
  "projects_count": 555,
  "free_ravelry_download": false,
  "download_url": "http://www.ravelry.com/purchase/briana-k-designs/952965"
}